<annotation>
	<folder>JPEGImages</folder>
	<filename>T_right79.png</filename>
	<path>/root/SSD-Tensorflow-On-Custom-Dataset/VOC2007/JPEGImages/T_right79.png</path>
	<source>
		<database>Unknown</database>
	</source>
	<size>
		<width>547</width>
		<height>435</height>
		<depth>3</depth>
	</size>
	<segmented>0</segmented>
	<object>
		<name>turn_right</name>
		<pose>Unspecified</pose>
		<truncated>0</truncated>
		<difficult>0</difficult>
		<bndbox>
			<xmin>15</xmin>
			<ymin>81</ymin>
			<xmax>305</xmax>
			<ymax>379</ymax>
		</bndbox>
	</object>
</annotation>
